neuroio/__init__.py
neuroio/auth/__init__.py
neuroio/auth/v1.py
neuroio/auth_token.py
neuroio/base.py
neuroio/billing/__init__.py
neuroio/billing/v1.py
neuroio/clients.py
neuroio/constants.py
neuroio/entries/__init__.py
neuroio/entries/v1.py
neuroio/groups/__init__.py
neuroio/groups/v1.py
neuroio/licenses/__init__.py
neuroio/licenses/sources/__init__.py
neuroio/licenses/sources/v1.py
neuroio/listeners.py
neuroio/lists/__init__.py
neuroio/lists/spaces/__init__.py
neuroio/lists/spaces/v1.py
neuroio/notifications/__init__.py
neuroio/notifications/v1.py
neuroio/persons/__init__.py
neuroio/persons/v1.py
neuroio/settings/__init__.py
neuroio/settings/v1.py
neuroio/sources/__init__.py
neuroio/sources/v1.py
neuroio/spaces/__init__.py
neuroio/spaces/v1.py
neuroio/streams/__init__.py
neuroio/streams/tokens/__init__.py
neuroio/streams/tokens/v1.py
neuroio/tokens/__init__.py
neuroio/tokens/v1.py
neuroio/utility/__init__.py
neuroio/utility/v1.py
neuroio/utils.py
neuroio/whoami/__init__.py
neuroio/whoami/v1.py
neuroio-0.1.2.dist-info/LICENSE
neuroio-0.1.2.dist-info/METADATA
neuroio-0.1.2.dist-info/WHEEL
neuroio-0.1.2.dist-info/RECORD
